MANIFEST.in
README.rst
setup.py
collective/__init__.py
collective.dancefloor.egg-info/PKG-INFO
collective.dancefloor.egg-info/SOURCES.txt
collective.dancefloor.egg-info/dependency_links.txt
collective.dancefloor.egg-info/entry_points.txt
collective.dancefloor.egg-info/namespace_packages.txt
collective.dancefloor.egg-info/not-zip-safe
collective.dancefloor.egg-info/requires.txt
collective.dancefloor.egg-info/top_level.txt
collective/dancefloor/__init__.py
collective/dancefloor/channels.py
collective/dancefloor/config.py
collective/dancefloor/configure.zcml
collective/dancefloor/exportimport.py
collective/dancefloor/extender.py
collective/dancefloor/i18n.sh
collective/dancefloor/indexer.py
collective/dancefloor/interfaces.py
collective/dancefloor/localroles.py
collective/dancefloor/monkey.py
collective/dancefloor/overrides.zcml
collective/dancefloor/tools.py
collective/dancefloor/upgrades.py
collective/dancefloor/upgrades.zcml
collective/dancefloor/utils.py
collective/dancefloor/vocabularies.py
collective/dancefloor/browser/__init__.py
collective/dancefloor/browser/clear_default_queue.py
collective/dancefloor/browser/configure.zcml
collective/dancefloor/browser/controlpanel-links.pt
collective/dancefloor/browser/controlpanel.pt
collective/dancefloor/browser/subscribe_view.pt
collective/dancefloor/browser/subscribe_view.py
collective/dancefloor/browser/views.py
collective/dancefloor/events/__init__.py
collective/dancefloor/events/configure.zcml
collective/dancefloor/events/local_newsletter.py
collective/dancefloor/locales/collective.dancefloor.pot
collective/dancefloor/locales/it/LC_MESSAGES/collective.dancefloor.mo
collective/dancefloor/locales/it/LC_MESSAGES/collective.dancefloor.po
collective/dancefloor/profiles/default/actions.xml
collective/dancefloor/profiles/default/browserlayer.xml
collective/dancefloor/profiles/default/dancefloor-various.txt
collective/dancefloor/profiles/default/metadata.xml
collective/dancefloor/profiles/default/rolemap.xml
collective/dancefloor/tests/__init__.py
collective/dancefloor/tests/base.py
collective/dancefloor/tests/test_dancefloor_enable.py
collective/dancefloor/tests/test_dancefloor_localsite.py
collective/dancefloor/tests/test_extender.py
docs/HISTORY.txt
docs/INSTALL.txt
docs/LICENSE.GPL
docs/LICENSE.txt