Metadata-Version: 1.1
Name: collective.dancefloor
Version: 1.0.2
Summary: S&D extension to allow local newsletters
Home-page: https://svn.plone.org/svn/collective/collective.dancefloor/trunk
Author: RedTurtle Technology
Author-email: sviluppoplone@redturtle.it
License: GPL
Platform: UNKNOWN
Classifier: Framework :: Plone
Classifier: Programming Language :: Python
Classifier: Framework :: Plone
Classifier: Framework :: Plone :: 3.3
Classifier: Framework :: Plone :: 4.0
Classifier: Framework :: Plone :: 4.2
Classifier: Development Status :: 4 - Beta
Classifier: Topic :: Software Development :: Libraries :: Python Modules
